example/__init__.py
example_cjrash_pypi-0.0.1.dist-info/LICENSE
example_cjrash_pypi-0.0.1.dist-info/METADATA
example_cjrash_pypi-0.0.1.dist-info/WHEEL
example_cjrash_pypi-0.0.1.dist-info/top_level.txt
example_cjrash_pypi-0.0.1.dist-info/RECORD
