Metadata-Version: 2.1
Name: example-cjrash-pypi
Version: 0.0.1
Summary: Trying to learn
Home-page: https://github.com/jordan-rash/pythonTest
Author: Jordan Rash
Author-email: cjr@cjrash.com
License: UNKNOWN
Platform: UNKNOWN
Classifier: Programming Language :: Python :: 3
Classifier: License :: OSI Approved :: MIT License
Classifier: Operating System :: OS Independent
Requires-Python: >=3.6
